pyfreeproxies/__init__.py
pyfreeproxies/models.py
pyfreeproxies/proxies.py
pyfreeproxies/proxyscrape.py
pyfreeproxies/utils.py
pyfreeproxies-0.2.3.dist-info/licenses/LICENSE
pyfreeproxies-0.2.3.dist-info/METADATA
pyfreeproxies-0.2.3.dist-info/WHEEL
pyfreeproxies-0.2.3.dist-info/top_level.txt
pyfreeproxies-0.2.3.dist-info/RECORD
