Metadata-Version: 2.4
Name: pyfreeproxies
Version: 0.2.3
Summary: Free to use http, socks4 and socks5 proxies
Home-page: https://github.com/Simatwa/pyfreeproxies
Author: Smartwa
Author-email: simatwacaleb@proton.me
Maintainer: Smartwa
License: GNUv3
Project-URL: Bug Report, https://github.com/Simatwa/pyfreeproxies/issues/new
Project-URL: Homepage, https://github.com/Simatwa/pyfreeproxies
Project-URL: Source Code, https://github.com/Simatwa/pyfreeproxies
Project-URL: Issue Tracker, https://github.com/Simatwa/pyfreeproxies/issues
Project-URL: Download, https://github.com/Simatwa/pyfreeproxies/releases
Project-URL: Documentation, https://github.com/Simatwa/pyfreeproxies/blob/main/docs
Keywords: freeproxies,proxies,socks4,socks5,http
Classifier: License :: OSI Approved :: GNU General Public License v3 (GPLv3)
Classifier: Intended Audience :: Developers
Classifier: Topic :: Internet :: Proxy Servers
Classifier: Topic :: Internet :: WWW/HTTP
Classifier: Topic :: Software Development :: Libraries :: Python Modules
Classifier: Programming Language :: Python :: 3 :: Only
Classifier: Programming Language :: Python :: 3.9
Classifier: Programming Language :: Python :: 3.10
Classifier: Programming Language :: Python :: 3.11
Classifier: Programming Language :: Python :: 3.12
Classifier: Programming Language :: Python :: 3.13
Classifier: Programming Language :: Python :: 3.14
Requires-Python: >=3.9
License-File: LICENSE
Requires-Dist: requests>=2.31.0
Requires-Dist: pydantic>=2.6.4
Dynamic: author
Dynamic: author-email
Dynamic: classifier
Dynamic: description
Dynamic: description-content-type
Dynamic: home-page
Dynamic: keywords
Dynamic: license
Dynamic: license-file
Dynamic: maintainer
Dynamic: project-url
Dynamic: requires-dist
Dynamic: requires-python
Dynamic: summary
